MANIFEST.in
setup.cfg
setup.py
plibfast/__init__.py
plibfast.egg-info/PKG-INFO
plibfast.egg-info/SOURCES.txt
plibfast.egg-info/dependency_links.txt
plibfast.egg-info/requires.txt
plibfast.egg-info/top_level.txt
plibfast/math/__init__.py
plibfast/math/__pycache__/__init__.cpython-35.pyc
plibfast/save/__init__.py
plibfast/src/align_wrapper.c
plibfast/src/align_wrapper.pyx
plibfast/src/alloc_aligned_type.c
plibfast/src/alloc_aligned_type.h
plibfast/src/plib_fast_reduction.h
plibfast/src/plib_vectorized.h
plibfast/src/reduction.c
plibfast/src/reduction.h