Metadata-Version: 1.1
Name: plibfast
Version: 1.0.2
Summary: Python wrapper for fast math library
Home-page: https://gitlab.in2p3.fr/CTA-LAPP/plibfast
Author: Pierre Aubert, Jean Jacquemier
Author-email: jean.jacquemier@lapp.in2p3.fr
License: BSD License
Platform: UNKNOWN
Classifier: Intended Audience :: Science/Research
Classifier: License :: OSI Approved :: BSD License
Classifier: Operating System :: OS Independent
Classifier: Programming Language :: C
Classifier: Programming Language :: Cython
Classifier: Programming Language :: Python :: 3
Classifier: Programming Language :: Python :: Implementation :: CPython
Classifier: Topic :: Scientific/Engineering :: Astronomy
Classifier: Development Status :: 3 - Alpha
